sirabus/__init__.py
sirabus/command_response.py
sirabus/hierarchical_topicmap.py
sirabus/message_pump.py
sirabus/publisher/__init__.py
sirabus/publisher/amqp_publisher.py
sirabus/publisher/inmemory_publisher.py
sirabus/publisher/pubsub_publisher.py
sirabus/publisher/py.typed
sirabus/publisher/redis_publisher.py
sirabus/publisher/sqs_publisher.py
sirabus/py.typed
sirabus/router/__init__.py
sirabus/router/amqp_command_router.py
sirabus/router/inmemory_command_router.py
sirabus/router/pubsub_command_router.py
sirabus/router/py.typed
sirabus/router/redis_command_router.py
sirabus/router/sqs_command_router.py
sirabus/serialization/__init__.py
sirabus/serialization/cloudevent_serialization.py
sirabus/serialization/py.typed
sirabus/serialization/pydantic_serialization.py
sirabus/servicebus/__init__.py
sirabus/servicebus/amqp_servicebus.py
sirabus/servicebus/inmemory_servicebus.py
sirabus/servicebus/pubsub_servicebus.py
sirabus/servicebus/py.typed
sirabus/servicebus/redis_servicebus.py
sirabus/servicebus/sqs_servicebus.py
sirabus/shared/pubsub.py
sirabus/shared/pubsub_config.py
sirabus/shared/py.typed
sirabus/shared/sqs_config.py
sirabus/topography/amqp/__init__.py
sirabus/topography/amqp/py.typed
sirabus/topography/pubsub/__init__.py
sirabus/topography/pubsub/py.typed
sirabus/topography/sqs/__init__.py
sirabus/topography/sqs/py.typed
sirabus-0.7.0.dist-info/WHEEL
sirabus-0.7.0.dist-info/METADATA
sirabus-0.7.0.dist-info/RECORD
