Metadata-Version: 2.3
Name: sirabus
Version: 0.7.0
Summary: Service Bus application pattern for Python with support for multiple messaging protocols.
Keywords: amqp,rabbitmq,sqs,redis,pubsub,cloudevents,event bus,message bus,message broker,service bus,event-driven,microservices,aws,gcp
Author: Jacob Reimers
Author-email: Jacob Reimers <pypi@reimers.io>
Requires-Dist: aett>=3.4.0
Requires-Dist: aio-pika>=9.5 ; extra == 'amqp'
Requires-Dist: cloudevents>=1.12.0 ; extra == 'cloudevents'
Requires-Dist: google-cloud-pubsub>=2.33 ; extra == 'pubsub'
Requires-Dist: redis>=6.4 ; extra == 'redis'
Requires-Dist: boto3>=1.40 ; extra == 'sqs'
Requires-Python: >=3.13
Provides-Extra: amqp
Provides-Extra: cloudevents
Provides-Extra: pubsub
Provides-Extra: redis
Provides-Extra: sqs
